ofrak/__init__.py
ofrak/__main__.py
ofrak/ofrak_context.py
ofrak/py.typed
ofrak/resource.py
ofrak/resource_view.py
ofrak/cli/__init__.py
ofrak/cli/ofrak_cli.py
ofrak/cli/command/__init__.py
ofrak/cli/command/deps.py
ofrak/cli/command/gui.py
ofrak/cli/command/identify.py
ofrak/cli/command/license.py
ofrak/cli/command/list.py
ofrak/cli/command/unpack.py
ofrak/component/__init__.py
ofrak/component/abstract.py
ofrak/component/analyzer.py
ofrak/component/identifier.py
ofrak/component/interface.py
ofrak/component/modifier.py
ofrak/component/packer.py
ofrak/component/unpacker.py
ofrak/core/__init__.py
ofrak/core/addressable.py
ofrak/core/apk.py
ofrak/core/architecture.py
ofrak/core/architecture_analysis.py
ofrak/core/basic_block.py
ofrak/core/binary.py
ofrak/core/binwalk.py
ofrak/core/bzip2.py
ofrak/core/checksum.py
ofrak/core/code_region.py
ofrak/core/comments.py
ofrak/core/complex_block.py
ofrak/core/cpio.py
ofrak/core/data.py
ofrak/core/decompilation.py
ofrak/core/dtb.py
ofrak/core/extfs.py
ofrak/core/filesystem.py
ofrak/core/flash.py
ofrak/core/free_space.py
ofrak/core/gzip.py
ofrak/core/ihex.py
ofrak/core/injector.py
ofrak/core/instruction.py
ofrak/core/iso9660.py
ofrak/core/java.py
ofrak/core/jffs2.py
ofrak/core/label.py
ofrak/core/lzma.py
ofrak/core/lzo.py
ofrak/core/magic.py
ofrak/core/memory_region.py
ofrak/core/openwrt.py
ofrak/core/program.py
ofrak/core/program_section.py
ofrak/core/py.typed
ofrak/core/rar.py
ofrak/core/run_script_modifier.py
ofrak/core/seven_zip.py
ofrak/core/squashfs.py
ofrak/core/strings.py
ofrak/core/strings_analyzer.py
ofrak/core/tar.py
ofrak/core/ubi.py
ofrak/core/ubifs.py
ofrak/core/uefi.py
ofrak/core/uf2.py
ofrak/core/uimage.py
ofrak/core/xattr_stub.py
ofrak/core/zip.py
ofrak/core/zlib.py
ofrak/core/zstd.py
ofrak/core/ecc/__init__.py
ofrak/core/ecc/abstract.py
ofrak/core/ecc/reedsolomon.py
ofrak/core/elf/__init__.py
ofrak/core/elf/analyzer.py
ofrak-3.3.0.dist-info/METADATA
ofrak-3.3.0.dist-info/WHEEL
ofrak-3.3.0.dist-info/entry_points.txt
ofrak-3.3.0.dist-info/top_level.txt
ofrak-3.3.0.dist-info/RECORD
ofrak-3.3.0.dist-info/licenses/LICENSE
