Metadata-Version: 2.4
Name: ofrak
Version: 3.3.0
Summary: A binary analysis and modification platform
Home-page: https://ofrak.com/
Download-URL: https://github.com/redballoonsecurity/ofrak
Author: Red Balloon Security
Author-email: ofrak@redballoonsecurity.com
License: Proprietary
Project-URL: Documentation, https://ofrak.com/docs/
Project-URL: Community License, https://github.com/redballoonsecurity/ofrak/blob/master/LICENSE
Project-URL: Commercial Licensing Information, https://ofrak.com/license/
Classifier: Programming Language :: Python :: 3
Classifier: Operating System :: OS Independent
Classifier: License :: Other/Proprietary License
Classifier: License :: Free To Use But Restricted
Classifier: License :: Free For Home Use
Classifier: Topic :: Security
Classifier: Typing :: Typed
Requires-Python: >=3.9
License-File: LICENSE
Requires-Dist: aiohttp>=3.12.14
Requires-Dist: aiohttp-cors~=0.7.0
Requires-Dist: beartype~=0.20.0
Requires-Dist: bincopy>=20.0.0
Requires-Dist: black>=23.3.0
Requires-Dist: cryptography>=44.0.3
Requires-Dist: fdt>=0.3.3
Requires-Dist: GitPython>=3.1.41
Requires-Dist: importlib-metadata>=4.13
Requires-Dist: intervaltree>=3.1.0
Requires-Dist: keystone-engine>=0.9.2
Requires-Dist: jefferson>=0.4.5; python_version >= "3.8"
Requires-Dist: lief>=0.16.1
Requires-Dist: ofrak_io==1.*,>=1.1.3
Requires-Dist: ofrak_type==2.*,>=2.3.0
Requires-Dist: ofrak_patch_maker==4.*,>=4.1.0
Requires-Dist: orjson>=3.10.16
Requires-Dist: pefile>=2023.2.7
Requires-Dist: pycdlib>=1.12.0
Requires-Dist: python-magic>=0.4.27; platform_system != "Windows"
Requires-Dist: python-magic-bin>=0.4.14; platform_system == "Windows"
Requires-Dist: reedsolo>=1.7.0
Requires-Dist: sortedcontainers>=2.2.2
Requires-Dist: synthol~=0.1.1
Requires-Dist: tempfile312~=1.0.1
Requires-Dist: typeguard~=2.13.3
Requires-Dist: ubi-reader>=0.8.12
Requires-Dist: xattr>=0.10.1; platform_system != "Windows"
Dynamic: author
Dynamic: author-email
Dynamic: classifier
Dynamic: description
Dynamic: description-content-type
Dynamic: download-url
Dynamic: home-page
Dynamic: license
Dynamic: license-file
Dynamic: project-url
Dynamic: requires-dist
Dynamic: requires-python
Dynamic: summary
